rand_engine/__init__.py
rand_engine/core/_ext_core.py
rand_engine/core/_np_core.py
rand_engine/core/_py_core.py
rand_engine/core/_spark_core.py
rand_engine/file_handlers/_writer_batch.py
rand_engine/file_handlers/_writer_stream.py
rand_engine/file_handlers/file_handler.py
rand_engine/file_handlers/fs_utils.py
rand_engine/file_handlers/writer.py
rand_engine/integrations/__init__.py
rand_engine/integrations/_base_handler.py
rand_engine/integrations/_duckdb_handler.py
rand_engine/integrations/_sqlite_handler.py
rand_engine/main/_cdc_generator.py
rand_engine/main/_constraints_handler.py
rand_engine/main/_rand_generator.py
rand_engine/main/data_generator.py
rand_engine/main/examples.py
rand_engine/main/spark_generator.py
rand_engine/templates/__init__.py
rand_engine/templates/i_random_spec.py
rand_engine/templates/web_server_logs.py
rand_engine/utils/logger.py
rand_engine/utils/stream_handler.py
rand_engine/utils/update.py
rand_engine/validators/__init__.py
rand_engine/validators/exceptions.py
rand_engine/validators/spec_validator.py
rand_engine-0.6.1.dist-info/METADATA
rand_engine-0.6.1.dist-info/WHEEL
rand_engine-0.6.1.dist-info/RECORD
