Metadata-Version: 2.4
Name: rand-engine
Version: 0.6.1
Summary: Rand Engine v2. Package with some methods to generate random data in different formats. Great to mock data while testing or developing.
Author: marcoaureliomenezes
Author-email: marcoaurelioreislima@gmail.com
Requires-Python: >=3.10,<4.0
Classifier: Programming Language :: Python :: 3
Classifier: Programming Language :: Python :: 3.10
Classifier: Programming Language :: Python :: 3.11
Classifier: Programming Language :: Python :: 3.12
Classifier: Programming Language :: Python :: 3.13
Classifier: Programming Language :: Python :: 3.14
Requires-Dist: duckdb (>=1.4.1,<2.0.0)
Requires-Dist: fastavro (>=1.10.0,<2.0.0)
Requires-Dist: fastparquet (>=2024.11.0,<2025.0.0)
Requires-Dist: numpy (>=2.1.1,<3.0.0)
Requires-Dist: pandas (>=2.2.2,<3.0.0)
Requires-Dist: pyarrow (>=19.0.0,<20.0.0)
Project-URL: Repository, https://github.com/marcoaureliomenezes/rand_engine
